llama_index/storage/docstore/elasticsearch/__init__.py
llama_index/storage/docstore/elasticsearch/base.py
llama_index_storage_docstore_elasticsearch-0.4.1.dist-info/METADATA
llama_index_storage_docstore_elasticsearch-0.4.1.dist-info/WHEEL
llama_index_storage_docstore_elasticsearch-0.4.1.dist-info/licenses/LICENSE
llama_index_storage_docstore_elasticsearch-0.4.1.dist-info/RECORD
